odoo/addons/hr_department_analytic/README.rst
odoo/addons/hr_department_analytic/__init__.py
odoo/addons/hr_department_analytic/__manifest__.py
odoo/addons/hr_department_analytic/i18n/es.po
odoo/addons/hr_department_analytic/i18n/eu_ES.po
odoo/addons/hr_department_analytic/i18n/hr_department_analytic.pot
odoo/addons/hr_department_analytic/i18n/it.po
odoo/addons/hr_department_analytic/models/__init__.py
odoo/addons/hr_department_analytic/models/hr_department.py
odoo/addons/hr_department_analytic/readme/CONTRIBUTORS.md
odoo/addons/hr_department_analytic/readme/DESCRIPTION.md
odoo/addons/hr_department_analytic/static/description/icon.png
odoo/addons/hr_department_analytic/static/description/index.html
odoo/addons/hr_department_analytic/views/hr_department.xml
odoo_addon_hr_department_analytic-16.0.1.0.0.7.dist-info/METADATA
odoo_addon_hr_department_analytic-16.0.1.0.0.7.dist-info/WHEEL
odoo_addon_hr_department_analytic-16.0.1.0.0.7.dist-info/top_level.txt
odoo_addon_hr_department_analytic-16.0.1.0.0.7.dist-info/RECORD
