Metadata-Version: 2.1
Name: odoo-addon-hr_department_analytic
Version: 16.0.1.0.0.7
Summary: This module allows to specify analytic account on hr department
Home-page: https://github.com/OCA/account-analytic
Author: ACSONE SA/NV,Odoo Community Association (OCA)
Author-email: support@odoo-community.org
License: AGPL-3
Classifier: Programming Language :: Python
Classifier: Framework :: Odoo
Classifier: Framework :: Odoo :: 16.0
Classifier: License :: OSI Approved :: GNU Affero General Public License v3
Requires-Python: >=3.10
Requires-Dist: odoo<16.1dev,>=16.0a
